LICENSE
README.rst
coscon/__init__.py
coscon/cmb.py
coscon/fits_helper.py
coscon/io_helper.py
coscon/toast_extras.py
coscon/toast_helper.py
coscon/util.py
coscon-0.1.1.dist-info/entry_points.txt
coscon-0.1.1.dist-info/LICENSE
coscon-0.1.1.dist-info/WHEEL
coscon-0.1.1.dist-info/METADATA
coscon-0.1.1.dist-info/RECORD
