Metadata-Version: 2.1
Name: coscon
Version: 0.1.1
Summary: Some convenience functions for Cosmology-related analysis.
Home-page: https://github.com/ickc/coscon
License: BSD-3-Clause
Keywords: cosmology,CMB
Author: Kolen Cheung
Author-email: christian.kolen@gmail.com
Requires-Python: >=3.8
Classifier: Development Status :: 4 - Beta
Classifier: Environment :: Console
Classifier: Intended Audience :: Developers
Classifier: License :: OSI Approved :: BSD License
Classifier: Operating System :: Microsoft :: Windows
Classifier: Operating System :: POSIX
Classifier: Operating System :: Unix
Classifier: Programming Language :: Python
Classifier: Programming Language :: Python :: 3
Classifier: Programming Language :: Python :: 3.8
Classifier: Programming Language :: Python :: 3.9
Classifier: Programming Language :: Python :: Implementation :: CPython
Classifier: Topic :: Software Development :: Build Tools
Classifier: Topic :: Utilities
Provides-Extra: docs
Provides-Extra: extras
Provides-Extra: mpi
Provides-Extra: tests
Requires-Dist: astropy (>=4,<5)
Requires-Dist: coloredlogs (>=14,<16); extra == "extras"
Requires-Dist: coverage; extra == "tests"
Requires-Dist: coveralls; extra == "tests"
Requires-Dist: defopt (>=6,<7)
Requires-Dist: flake8; extra == "tests"
Requires-Dist: h5py (>=3,<4)
Requires-Dist: healpy (>=1,<2)
Requires-Dist: matplotlib (>=3,<4)
Requires-Dist: mpi4py (>=3,<4); extra == "mpi"
Requires-Dist: numba (>=0.52)
Requires-Dist: numba_quaternion (>=0.2,<1)
Requires-Dist: numpy (>=1,<2)
Requires-Dist: pandas (>=1,<2)
Requires-Dist: plotly (>=4,<5)
Requires-Dist: pygments-style-solarized; extra == "docs"
Requires-Dist: pysm3 (>=3,<4)
Requires-Dist: pytest-cov; extra == "tests"
Requires-Dist: pytest-mpi; extra == "tests"
Requires-Dist: pytest-parallel; extra == "tests"
Requires-Dist: pytest; extra == "tests"
Requires-Dist: pyyaml (>=5,<6)
Requires-Dist: schema (>=0.7)
Requires-Dist: seaborn (>=0.11)
Requires-Dist: sphinx (>=3.3,<4.0); extra == "docs"
Requires-Dist: sphinx-bootstrap-theme; extra == "docs"
Requires-Dist: sphinxcontrib-apidoc; extra == "docs"
Requires-Dist: tabulate (>=0.8,<0.9)
Requires-Dist: toast-cmb (>=2,<3)
Requires-Dist: toml (>=0.10)
Requires-Dist: yamlloader (>=0.5)
Project-URL: Documentation, https://ickc.github.io/coscon
Project-URL: Repository, https://github.com/ickc/coscon
